setup.cfg
setup.py
mtgsdk/__init__.py
mtgsdk/card.py
mtgsdk/changelog.py
mtgsdk/config.py
mtgsdk/querybuilder.py
mtgsdk/restclient.py
mtgsdk/set.py
mtgsdk/subtype.py
mtgsdk/supertype.py
mtgsdk/type.py
mtgsdk.egg-info/PKG-INFO
mtgsdk.egg-info/SOURCES.txt
mtgsdk.egg-info/dependency_links.txt
mtgsdk.egg-info/entry_points.txt
mtgsdk.egg-info/requires.txt
mtgsdk.egg-info/top_level.txt
tests/__init__.py
tests/test_card.py
tests/test_changelog.py
tests/test_config.py
tests/test_set.py
tests/test_subtype.py
tests/test_supertype.py
tests/test_type.py