Metadata-Version: 1.1
Name: mtgsdk
Version: 1.0.0
Summary: Magic: The Gathering SDK for magicthegathering.io
Home-page: https://github.com/MagicTheGathering/mtg-sdk-python
Author: Andrew Backes
Author-email: backes.andrew@gmail.com
License: MIT
Download-URL: https://github.com/MagicTheGathering/mtg-sdk-python/tarball/1.0.0
Keywords: mtg sdk magic gathering gatherer api rest
Platform: UNKNOWN
Classifier: Development Status :: 4 - Beta
Classifier: Intended Audience :: Developers
Classifier: License :: OSI Approved :: MIT License
Classifier: Natural Language :: English
Classifier: Operating System :: Unix
Classifier: Programming Language :: Python :: 3.4
Classifier: Operating System :: OS Independent
